toshl
