Metadata-Version: 1.1
Name: toshl
Version: 0.0.3
Summary: Python client library for Toshl API.
Home-page: https://github.com/andreagrandi/toshl-python
Author: Andrea Grandi
Author-email: a.grandi@gmail.com
License: MIT
Download-URL: https://github.com/andreagrandi/toshl-python/tarball/0.0.3
Platform: any
